{
  "classname": null,
  "name": null,
  "animation": {
    "classname": null,
    "name": "AnimationManager",
    "actionlist": []
  },
  "dataScale": 1,
  "designHeight": 640,
  "designWidth": 960,
  "textures": [],
  "texturesPng": [
    "UI resource/common/bottom_9 .png",
    "button_normal.png",
    "button_pressed.png",
    "UI resource/common/bg.png"
  ],
  "version": "1.6.0.0",
  "widgetTree": {
    "classname": "Panel",
    "name": null,
    "children": [
      {
        "classname": "Panel",
        "name": null,
        "children": [
          {
            "classname": "Panel",
            "name": null,
            "children": [
              {
                "classname": "Panel",
                "name": null,
                "children": [
                  {
                    "classname": "Label",
                    "name": null,
                    "children": [],
                    "options": {
                      "__type": "LabelSurrogate:#EditorCommon.JsonModel.Component.GUI",
                      "classname": "Label",
                      "name": "Txt_Title",
                      "ZOrder": 0,
                      "actiontag": 35480477,
                      "anchorPointX": 0.5,
                      "anchorPointY": 0.5,
                      "classType": "CocoStudio.EngineAdapterWrap.CSLabel",
                      "colorB": 0,
                      "colorG": 0,
                      "colorR": 255,
                      "customProperty": "",
                      "flipX": false,
                      "flipY": false,
                      "height": 35,
                      "ignoreSize": true,
                      "layoutParameter": {
                        "classname": null,
                        "name": null,
                        "align": 2,
                        "gravity": 0,
                        "layoutEageType": 0,
                        "layoutNormalHorizontal": 0,
                        "layoutNormalVertical": 0,
                        "layoutParentHorizontal": 0,
                        "layoutParentVertical": 0,
                        "marginDown": 0,
                        "marginLeft": 0,
                        "marginRight": 0,
                        "marginTop": 103,
                        "relativeName": "Txt_Title",
                        "relativeToName": "Pnl_Content",
                        "type": 2
                      },
                      "opacity": 255,
                      "positionPercentX": 0.5,
                      "positionPercentY": 0.6257764,
                      "positionType": 0,
                      "rotation": 0,
                      "scaleX": 1,
                      "scaleY": 1,
                      "sizePercentX": 0.5260116,
                      "sizePercentY": 0.108695649,
                      "sizeType": 0,
                      "tag": 21921,
                      "touchAble": false,
                      "useMergedTexture": false,
                      "visible": true,
                      "width": 182,
                      "x": 173,
                      "y": 201,
                      "areaHeight": 0,
                      "areaWidth": 0,
                      "fontFile": null,
                      "fontName": "微软雅黑",
                      "fontSize": 26,
                      "hAlignment": 1,
                      "text": "确定踢出此人？",
                      "touchScaleEnable": false,
                      "vAlignment": 1
                    }
                  },
                  {
                    "classname": "Button",
                    "name": null,
                    "children": [],
                    "options": {
                      "__type": "ButtonSurrogate:#EditorCommon.JsonModel.Component.GUI",
                      "classname": "Button",
                      "name": "Btn_Confirm",
                      "ZOrder": 0,
                      "actiontag": 12559127,
                      "anchorPointX": 0.5,
                      "anchorPointY": 0.5,
                      "classType": "CocoStudio.EngineAdapterWrap.CSButton",
                      "colorB": 255,
                      "colorG": 248,
                      "colorR": 240,
                      "customProperty": "",
                      "flipX": false,
                      "flipY": false,
                      "height": 40,
                      "ignoreSize": false,
                      "layoutParameter": {
                        "classname": null,
                        "name": null,
                        "align": 2,
                        "gravity": 0,
                        "layoutEageType": 0,
                        "layoutNormalHorizontal": 0,
                        "layoutNormalVertical": 0,
                        "layoutParentHorizontal": 0,
                        "layoutParentVertical": 0,
                        "marginDown": 0,
                        "marginLeft": 0,
                        "marginRight": 0,
                        "marginTop": 198,
                        "relativeName": "Btn_Confirm",
                        "relativeToName": "Pnl_Content",
                        "type": 2
                      },
                      "opacity": 255,
                      "positionPercentX": 0.5,
                      "positionPercentY": 0.322981358,
                      "positionType": 0,
                      "rotation": 0,
                      "scaleX": 1.33172965,
                      "scaleY": 1.33172965,
                      "sizePercentX": 0.3236994,
                      "sizePercentY": 0.124223605,
                      "sizeType": 0,
                      "tag": 21928,
                      "touchAble": true,
                      "useMergedTexture": false,
                      "visible": true,
                      "width": 112,
                      "x": 173,
                      "y": 104,
                      "capInsetsHeight": 1,
                      "capInsetsWidth": 1,
                      "capInsetsX": 0,
                      "capInsetsY": 0,
                      "disabled": null,
                      "disabledData": {
                        "path": null,
                        "plistFile": null,
                        "resourceType": 0
                      },
                      "fontName": "微软雅黑",
                      "fontSize": 22,
                      "fontType": 0,
                      "normal": null,
                      "normalData": {
                        "path": "button_normal.png",
                        "plistFile": "",
                        "resourceType": 0
                      },
                      "pressed": null,
                      "pressedData": {
                        "path": "button_pressed.png",
                        "plistFile": "",
                        "resourceType": 0
                      },
                      "scale9Enable": false,
                      "scale9Height": 40,
                      "scale9Width": 112,
                      "text": "确定",
                      "textColorB": 255,
                      "textColorG": 255,
                      "textColorR": 255
                    }
                  }
                ],
                "options": {
                  "__type": "PanelSurrogate:#EditorCommon.JsonModel.Component.GUI",
                  "classname": "Panel",
                  "name": "Pnl_Content",
                  "ZOrder": 0,
                  "actiontag": 11398815,
                  "anchorPointX": 0,
                  "anchorPointY": 0,
                  "classType": "CocoStudio.EngineAdapterWrap.CSPanel",
                  "colorB": 255,
                  "colorG": 255,
                  "colorR": 255,
                  "customProperty": "",
                  "flipX": false,
                  "flipY": false,
                  "height": 322,
                  "ignoreSize": false,
                  "layoutParameter": {
                    "classname": null,
                    "name": null,
                    "align": 5,
                    "gravity": 0,
                    "layoutEageType": 0,
                    "layoutNormalHorizontal": 0,
                    "layoutNormalVertical": 0,
                    "layoutParentHorizontal": 0,
                    "layoutParentVertical": 0,
                    "marginDown": 0,
                    "marginLeft": 0,
                    "marginRight": 0,
                    "marginTop": 0,
                    "relativeName": "Pnl_Content",
                    "relativeToName": "Pnl_Content_Member",
                    "type": 2
                  },
                  "opacity": 255,
                  "positionPercentX": 0.173584908,
                  "positionPercentY": -0.0962962955,
                  "positionType": 0,
                  "rotation": 0,
                  "scaleX": 1,
                  "scaleY": 1,
                  "sizePercentX": 0.6528302,
                  "sizePercentY": 1.19259262,
                  "sizeType": 0,
                  "tag": 21920,
                  "touchAble": true,
                  "useMergedTexture": false,
                  "visible": true,
                  "width": 346,
                  "x": 92,
                  "y": -26,
                  "adaptScreen": false,
                  "backGroundImage": null,
                  "backGroundImageData": {
                    "path": "UI resource/common/bottom_9 .png",
                    "plistFile": "",
                    "resourceType": 0
                  },
                  "backGroundScale9Enable": true,
                  "bgColorB": 255,
                  "bgColorG": 200,
                  "bgColorOpacity": 100,
                  "bgColorR": 150,
                  "bgEndColorB": 255,
                  "bgEndColorG": 200,
                  "bgEndColorR": 150,
                  "bgStartColorB": 255,
                  "bgStartColorG": 255,
                  "bgStartColorR": 255,
                  "capInsetsHeight": 4,
                  "capInsetsWidth": 4,
                  "capInsetsX": 128,
                  "capInsetsY": 128,
                  "clipAble": false,
                  "colorType": 0,
                  "layoutType": 3,
                  "vectorX": 0,
                  "vectorY": -0.5
                }
              }
            ],
            "options": {
              "__type": "PanelSurrogate:#EditorCommon.JsonModel.Component.GUI",
              "classname": "Panel",
              "name": "Pnl_Content_Member",
              "ZOrder": 0,
              "actiontag": 23636156,
              "anchorPointX": 0,
              "anchorPointY": 0,
              "classType": "CocoStudio.EngineAdapterWrap.CSPanel",
              "colorB": 255,
              "colorG": 255,
              "colorR": 255,
              "customProperty": "",
              "flipX": false,
              "flipY": false,
              "height": 270,
              "ignoreSize": false,
              "layoutParameter": {
                "classname": null,
                "name": null,
                "align": 1,
                "gravity": 0,
                "layoutEageType": 0,
                "layoutNormalHorizontal": 0,
                "layoutNormalVertical": 0,
                "layoutParentHorizontal": 0,
                "layoutParentVertical": 0,
                "marginDown": 0,
                "marginLeft": 200,
                "marginRight": 0,
                "marginTop": 94,
                "relativeName": "Pnl_Content_Member",
                "relativeToName": "Pnl_Content_Main",
                "type": 2
              },
              "opacity": 255,
              "positionPercentX": 0.25316456,
              "positionPercentY": 0.09,
              "positionType": 0,
              "rotation": 0,
              "scaleX": 1,
              "scaleY": 1,
              "sizePercentX": 0.6708861,
              "sizePercentY": 0.675,
              "sizeType": 0,
              "tag": 21919,
              "touchAble": false,
              "useMergedTexture": false,
              "visible": true,
              "width": 530,
              "x": 200,
              "y": 36,
              "adaptScreen": false,
              "backGroundImage": null,
              "backGroundImageData": null,
              "backGroundScale9Enable": false,
              "bgColorB": 255,
              "bgColorG": 200,
              "bgColorOpacity": 100,
              "bgColorR": 150,
              "bgEndColorB": 255,
              "bgEndColorG": 200,
              "bgEndColorR": 150,
              "bgStartColorB": 255,
              "bgStartColorG": 255,
              "bgStartColorR": 255,
              "capInsetsHeight": 1,
              "capInsetsWidth": 1,
              "capInsetsX": 0,
              "capInsetsY": 0,
              "clipAble": false,
              "colorType": 0,
              "layoutType": 3,
              "vectorX": 0,
              "vectorY": -0.5
            }
          }
        ],
        "options": {
          "__type": "PanelSurrogate:#EditorCommon.JsonModel.Component.GUI",
          "classname": "Panel",
          "name": "Pnl_Content_Main",
          "ZOrder": 1,
          "actiontag": 55944358,
          "anchorPointX": 0,
          "anchorPointY": 0,
          "classType": "CocoStudio.EngineAdapterWrap.CSPanel",
          "colorB": 255,
          "colorG": 255,
          "colorR": 255,
          "customProperty": "",
          "flipX": false,
          "flipY": false,
          "height": 400,
          "ignoreSize": false,
          "layoutParameter": {
            "classname": null,
            "name": null,
            "align": 2,
            "gravity": 0,
            "layoutEageType": 0,
            "layoutNormalHorizontal": 0,
            "layoutNormalVertical": 0,
            "layoutParentHorizontal": 0,
            "layoutParentVertical": 0,
            "marginDown": 0,
            "marginLeft": 0,
            "marginRight": 0,
            "marginTop": 140,
            "relativeName": "Pnl_Content_Main",
            "relativeToName": "Pnl_Exit",
            "type": 2
          },
          "opacity": 255,
          "positionPercentX": 0.0885416642,
          "positionPercentY": 0.15625,
          "positionType": 0,
          "rotation": 0,
          "scaleX": 1,
          "scaleY": 1,
          "sizePercentX": 0.8229167,
          "sizePercentY": 0.625,
          "sizeType": 0,
          "tag": 21918,
          "touchAble": false,
          "useMergedTexture": false,
          "visible": true,
          "width": 790,
          "x": 85,
          "y": 100,
          "adaptScreen": false,
          "backGroundImage": null,
          "backGroundImageData": null,
          "backGroundScale9Enable": false,
          "bgColorB": 255,
          "bgColorG": 200,
          "bgColorOpacity": 100,
          "bgColorR": 150,
          "bgEndColorB": 255,
          "bgEndColorG": 200,
          "bgEndColorR": 150,
          "bgStartColorB": 255,
          "bgStartColorG": 255,
          "bgStartColorR": 255,
          "capInsetsHeight": 1,
          "capInsetsWidth": 1,
          "capInsetsX": 0,
          "capInsetsY": 0,
          "clipAble": false,
          "colorType": 0,
          "layoutType": 3,
          "vectorX": 0,
          "vectorY": -0.5
        }
      },
      {
        "classname": "ImageView",
        "name": null,
        "children": [],
        "options": {
          "__type": "ImageViewSurrogate:#EditorCommon.JsonModel.Component.GUI",
          "classname": "ImageView",
          "name": "bk_0",
          "ZOrder": 0,
          "actiontag": 49678823,
          "anchorPointX": 0.5,
          "anchorPointY": 0.5,
          "classType": "CocoStudio.EngineAdapterWrap.CSImageView",
          "colorB": 255,
          "colorG": 255,
          "colorR": 255,
          "customProperty": "",
          "flipX": false,
          "flipY": false,
          "height": 318,
          "ignoreSize": false,
          "layoutParameter": {
            "classname": null,
            "name": null,
            "align": 1,
            "gravity": 0,
            "layoutEageType": 0,
            "layoutNormalHorizontal": 0,
            "layoutNormalVertical": 0,
            "layoutParentHorizontal": 0,
            "layoutParentVertical": 0,
            "marginDown": 0,
            "marginLeft": 424,
            "marginRight": 0,
            "marginTop": 210,
            "relativeName": "bk_0",
            "relativeToName": "Pnl_Exit",
            "type": 2
          },
          "opacity": 99,
          "positionPercentX": 0.576041639,
          "positionPercentY": 0.4234375,
          "positionType": 0,
          "rotation": 0,
          "scaleX": 0.944629,
          "scaleY": 0.6945193,
          "sizePercentX": 0.26875,
          "sizePercentY": 0.496875,
          "sizeType": 0,
          "tag": 70845,
          "touchAble": false,
          "useMergedTexture": false,
          "visible": true,
          "width": 258,
          "x": 553,
          "y": 271,
          "capInsetsHeight": 1,
          "capInsetsWidth": 1,
          "capInsetsX": 0,
          "capInsetsY": 0,
          "fileName": null,
          "fileNameData": {
            "path": "UI resource/common/bg.png",
            "plistFile": "",
            "resourceType": 0
          },
          "scale9Enable": false,
          "scale9Height": 318,
          "scale9Width": 258
        }
      }
    ],
    "options": {
      "__type": "PanelSurrogate:#EditorCommon.JsonModel.Component.GUI",
      "classname": "Panel",
      "name": "Pnl_Exit",
      "ZOrder": 1,
      "actiontag": -1,
      "anchorPointX": 0,
      "anchorPointY": 0,
      "classType": "CocoStudio.EngineAdapterWrap.CSPanel",
      "colorB": 255,
      "colorG": 255,
      "colorR": 255,
      "customProperty": "",
      "flipX": false,
      "flipY": false,
      "height": 640,
      "ignoreSize": false,
      "layoutParameter": null,
      "opacity": 255,
      "positionPercentX": 0,
      "positionPercentY": 0,
      "positionType": 0,
      "rotation": 0,
      "scaleX": 1,
      "scaleY": 1,
      "sizePercentX": 1,
      "sizePercentY": 1,
      "sizeType": 0,
      "tag": 91,
      "touchAble": false,
      "useMergedTexture": false,
      "visible": true,
      "width": 960,
      "x": 0,
      "y": 0,
      "adaptScreen": true,
      "backGroundImage": null,
      "backGroundImageData": null,
      "backGroundScale9Enable": false,
      "bgColorB": 170,
      "bgColorG": 205,
      "bgColorOpacity": 102,
      "bgColorR": 102,
      "bgEndColorB": 255,
      "bgEndColorG": 200,
      "bgEndColorR": 150,
      "bgStartColorB": 255,
      "bgStartColorG": 255,
      "bgStartColorR": 255,
      "capInsetsHeight": 1,
      "capInsetsWidth": 1,
      "capInsetsX": 0,
      "capInsetsY": 0,
      "clipAble": false,
      "colorType": 0,
      "layoutType": 3,
      "vectorX": 0,
      "vectorY": -0.5
    }
  }
}