{"1000":{"base_id":10001,"type":1,"count":1,"exp":100,"money":1000,"name":93001,"icon":0,"desc":93101},"1001":{"base_id":10002,"type":1,"count":2,"exp":140,"money":1000,"name":93002,"icon":0,"desc":93101},"1002":{"base_id":10003,"type":1,"count":3,"exp":200,"money":1000,"name":93003,"icon":0,"desc":93101},"1003":{"base_id":11001,"type":2,"count":1,"exp":100,"money":1000,"name":93004,"icon":0,"desc":93102},"1004":{"base_id":11002,"type":2,"count":2,"exp":140,"money":1000,"name":93005,"icon":0,"desc":93102},"1005":{"base_id":11003,"type":2,"count":3,"exp":200,"money":1000,"name":93006,"icon":0,"desc":93102},"1006":{"base_id":12001,"type":3,"count":1,"exp":100,"money":1000,"name":93007,"icon":0,"desc":93103},"1007":{"base_id":12002,"type":3,"count":2,"exp":140,"money":1000,"name":93008,"icon":0,"desc":93103},"1008":{"base_id":12003,"type":3,"count":3,"exp":200,"money":1000,"name":93009,"icon":0,"desc":93103},"1009":{"base_id":13001,"type":4,"count":1,"exp":100,"money":1000,"name":93010,"icon":0,"desc":93104},"1010":{"base_id":13002,"type":4,"count":2,"exp":140,"money":1000,"name":93011,"icon":0,"desc":93104},"1011":{"base_id":13003,"type":4,"count":3,"exp":200,"money":1000,"name":93012,"icon":0,"desc":93104},"1012":{"base_id":14001,"type":5,"count":1,"exp":140,"money":1000,"name":93013,"icon":0,"desc":93105}}